.DS_Store
JpGeocode/JpGeocode.py
JpGeocode/__init__.py
JpGeocode/data/jp_geocode.json
JpGeocode-0.3.1.dist-info/DESCRIPTION.rst
JpGeocode-0.3.1.dist-info/METADATA
JpGeocode-0.3.1.dist-info/RECORD
JpGeocode-0.3.1.dist-info/WHEEL
JpGeocode-0.3.1.dist-info/metadata.json
JpGeocode-0.3.1.dist-info/top_level.txt
