Metadata-Version: 2.0
Name: JpGeocode
Version: 0.3.1
Summary: Search coordinates from municipalities in Japan
Home-page: https://github.com/0x0u/JpGeocode
Author: m0zu
Author-email: m0zurillex@gmail.com
License: MIT
Keywords: Python3 japan geocoding
Platform: UNKNOWN
Classifier: Programming Language :: Python :: 3.6
